[{"deaths": {"value": 0}, "active": {"value": 32}, "confirmed": {"value": 40}, "recovered": {"value": 8}, "dateRecorded": "2020-04-25"}, {"deaths": {"value": 0}, "active": {"value": 31}, "confirmed": {"value": 46}, "recovered": {"value": 15}, "dateRecorded": "2020-04-26"}, {"deaths": {"value": 0}, "active": {"value": 31}, "confirmed": {"value": 46}, "recovered": {"value": 15}, "dateRecorded": "2020-04-27"}, {"deaths": {"value": 0}, "active": {"value": 31}, "confirmed": {"value": 46}, "recovered": {"value": 15}, "dateRecorded": "2020-04-28"}, {"deaths": {"value": 2}, "active": {"value": 31}, "confirmed": {"value": 52}, "recovered": {"value": 19}, "dateRecorded": "2020-04-29"}, {"deaths": {"value": 2}, "active": {"value": 31}, "confirmed": {"value": 52}, "recovered": {"value": 19}, "dateRecorded": "2020-04-30"}, {"deaths": {"value": 5}, "active": {"value": 35}, "confirmed": {"value": 73}, "recovered": {"value": 33}, "dateRecorded": "2020-05-01"}, {"deaths": {"value": 5}, "active": {"value": 35}, "confirmed": {"value": 73}, "recovered": {"value": 33}, "dateRecorded": "2020-05-02"}, {"deaths": {"value": 10}, "active": {"value": 68}, "confirmed": {"value": 117}, "recovered": {"value": 39}, "dateRecorded": "2020-05-03"}, {"deaths": {"value": 10}, "active": {"value": 68}, "confirmed": {"value": 117}, "recovered": {"value": 39}, "dateRecorded": "2020-05-04"}, {"deaths": {"value": 10}, "active": {"value": 68}, "confirmed": {"value": 117}, "recovered": {"value": 39}, "dateRecorded": "2020-05-05"}, {"deaths": {"value": 17}, "active": {"value": 110}, "confirmed": {"value": 170}, "recovered": {"value": 43}, "dateRecorded": "2020-05-06"}, {"deaths": {"value": 17}, "active": {"value": 110}, "confirmed": {"value": 170}, "recovered": {"value": 43}, "dateRecorded": "2020-05-07"}, {"deaths": {"value": 27}, "active": {"value": 176}, "confirmed": {"value": 253}, "recovered": {"value": 50}, "dateRecorded": "2020-05-08"}, {"deaths": {"value": 28}, "active": {"value": 182}, "confirmed": {"value": 260}, "recovered": {"value": 50}, "dateRecorded": "2020-05-09"}, {"deaths": {"value": 31}, "active": {"value": 238}, "confirmed": {"value": 322}, "recovered": {"value": 53}, "dateRecorded": "2020-05-10"}, {"deaths": {"value": 31}, "active": {"value": 238}, "confirmed": {"value": 322}, "recovered": {"value": 53}, "dateRecorded": "2020-05-11"}, {"deaths": {"value": 31}, "active": {"value": 238}, "confirmed": {"value": 322}, "recovered": {"value": 53}, "dateRecorded": "2020-05-12"}, {"deaths": {"value": 40}, "active": {"value": 241}, "confirmed": {"value": 357}, "recovered": {"value": 76}, "dateRecorded": "2020-05-13"}, {"deaths": {"value": 42}, "active": {"value": 252}, "confirmed": {"value": 372}, "recovered": {"value": 78}, "dateRecorded": "2020-05-14"}, {"deaths": {"value": 46}, "active": {"value": 270}, "confirmed": {"value": 399}, "recovered": {"value": 83}, "dateRecorded": "2020-05-15"}, {"deaths": {"value": 48}, "active": {"value": 292}, "confirmed": {"value": 428}, "recovered": {"value": 88}, "dateRecorded": "2020-05-16"}, {"deaths": {"value": 50}, "active": {"value": 313}, "confirmed": {"value": 474}, "recovered": {"value": 111}, "dateRecorded": "2020-05-17"}, {"deaths": {"value": 53}, "active": {"value": 333}, "confirmed": {"value": 503}, "recovered": {"value": 117}, "dateRecorded": "2020-05-18"}, {"deaths": {"value": 53}, "active": {"value": 349}, "confirmed": {"value": 519}, "recovered": {"value": 117}, "dateRecorded": "2020-05-19"}, {"deaths": {"value": 56}, "active": {"value": 350}, "confirmed": {"value": 545}, "recovered": {"value": 139}, "dateRecorded": "2020-05-20"}, {"deaths": {"value": 57}, "active": {"value": 331}, "confirmed": {"value": 565}, "recovered": {"value": 177}, "dateRecorded": "2020-05-21"}, {"deaths": {"value": 58}, "active": {"value": 344}, "confirmed": {"value": 588}, "recovered": {"value": 186}, "dateRecorded": "2020-05-22"}, {"deaths": {"value": 58}, "active": {"value": 357}, "confirmed": {"value": 611}, "recovered": {"value": 196}, "dateRecorded": "2020-05-23"}, {"deaths": {"value": 60}, "active": {"value": 384}, "confirmed": {"value": 648}, "recovered": {"value": 204}, "dateRecorded": "2020-05-24"}, {"deaths": {"value": 60}, "active": {"value": 400}, "confirmed": {"value": 675}, "recovered": {"value": 215}, "dateRecorded": "2020-05-25"}, {"deaths": {"value": 61}, "active": {"value": 382}, "confirmed": {"value": 687}, "recovered": {"value": 244}, "dateRecorded": "2020-05-26"}, {"deaths": {"value": 62}, "active": {"value": 335}, "confirmed": {"value": 700}, "recovered": {"value": 303}, "dateRecorded": "2020-05-27"}, {"deaths": {"value": 64}, "active": {"value": 292}, "confirmed": {"value": 715}, "recovered": {"value": 359}, "dateRecorded": "2020-05-28"}, {"deaths": {"value": 65}, "active": {"value": 248}, "confirmed": {"value": 726}, "recovered": {"value": 413}, "dateRecorded": "2020-05-29"}, {"deaths": {"value": 65}, "active": {"value": 250}, "confirmed": {"value": 759}, "recovered": {"value": 444}, "dateRecorded": "2020-05-30"}, {"deaths": {"value": 65}, "active": {"value": 224}, "confirmed": {"value": 759}, "recovered": {"value": 470}, "dateRecorded": "2020-05-31"}, {"deaths": {"value": 65}, "active": {"value": 222}, "confirmed": {"value": 778}, "recovered": {"value": 491}, "dateRecorded": "2020-06-01"}, {"deaths": {"value": 66}, "active": {"value": 185}, "confirmed": {"value": 790}, "recovered": {"value": 539}, "dateRecorded": "2020-06-02"}, {"deaths": {"value": 66}, "active": {"value": 175}, "confirmed": {"value": 803}, "recovered": {"value": 562}, "dateRecorded": "2020-06-03"}, {"deaths": {"value": 66}, "active": {"value": 164}, "confirmed": {"value": 820}, "recovered": {"value": 590}, "dateRecorded": "2020-06-04"}, {"deaths": {"value": 66}, "active": {"value": 129}, "confirmed": {"value": 828}, "recovered": {"value": 633}, "dateRecorded": "2020-06-05"}, {"deaths": {"value": 68}, "active": {"value": 111}, "confirmed": {"value": 836}, "recovered": {"value": 657}, "dateRecorded": "2020-06-06"}, {"deaths": {"value": 69}, "active": {"value": 95}, "confirmed": {"value": 836}, "recovered": {"value": 672}, "dateRecorded": "2020-06-07"}, {"deaths": {"value": 69}, "active": {"value": 96}, "confirmed": {"value": 837}, "recovered": {"value": 672}, "dateRecorded": "2020-06-08"}, {"deaths": {"value": 70}, "active": {"value": 84}, "confirmed": {"value": 839}, "recovered": {"value": 685}, "dateRecorded": "2020-06-09"}, {"deaths": {"value": 71}, "active": {"value": 67}, "confirmed": {"value": 844}, "recovered": {"value": 706}, "dateRecorded": "2020-06-10"}, {"deaths": {"value": 72}, "active": {"value": 68}, "confirmed": {"value": 846}, "recovered": {"value": 706}, "dateRecorded": "2020-06-11"}, {"deaths": {"value": 72}, "active": {"value": 70}, "confirmed": {"value": 848}, "recovered": {"value": 706}, "dateRecorded": "2020-06-12"}, {"deaths": {"value": 72}, "active": {"value": 65}, "confirmed": {"value": 848}, "recovered": {"value": 711}, "dateRecorded": "2020-06-13"}, {"deaths": {"value": 72}, "active": {"value": 58}, "confirmed": {"value": 848}, "recovered": {"value": 718}, "dateRecorded": "2020-06-14"}, {"deaths": {"value": 73}, "active": {"value": 57}, "confirmed": {"value": 850}, "recovered": {"value": 720}, "dateRecorded": "2020-06-15"}, {"deaths": {"value": 73}, "active": {"value": 57}, "confirmed": {"value": 850}, "recovered": {"value": 720}, "dateRecorded": "2020-06-16"}, {"deaths": {"value": 74}, "active": {"value": 59}, "confirmed": {"value": 853}, "recovered": {"value": 720}, "dateRecorded": "2020-06-17"}, {"deaths": {"value": 74}, "active": {"value": 59}, "confirmed": {"value": 854}, "recovered": {"value": 721}, "dateRecorded": "2020-06-18"}, {"deaths": {"value": 74}, "active": {"value": 47}, "confirmed": {"value": 854}, "recovered": {"value": 733}, "dateRecorded": "2020-06-19"}, {"deaths": {"value": 74}, "active": {"value": 42}, "confirmed": {"value": 858}, "recovered": {"value": 742}, "dateRecorded": "2020-06-20"}, {"deaths": {"value": 74}, "active": {"value": 38}, "confirmed": {"value": 858}, "recovered": {"value": 746}, "dateRecorded": "2020-06-21"}, {"deaths": {"value": 74}, "active": {"value": 32}, "confirmed": {"value": 858}, "recovered": {"value": 752}, "dateRecorded": "2020-06-22"}, {"deaths": {"value": 74}, "active": {"value": 29}, "confirmed": {"value": 858}, "recovered": {"value": 755}, "dateRecorded": "2020-06-23"}, {"deaths": {"value": 74}, "active": {"value": 29}, "confirmed": {"value": 860}, "recovered": {"value": 757}, "dateRecorded": "2020-06-24"}, {"deaths": {"value": 74}, "active": {"value": 16}, "confirmed": {"value": 860}, "recovered": {"value": 770}, "dateRecorded": "2020-06-25"}, {"deaths": {"value": 74}, "active": {"value": 15}, "confirmed": {"value": 863}, "recovered": {"value": 774}, "dateRecorded": "2020-06-26"}, {"deaths": {"value": 74}, "active": {"value": 13}, "confirmed": {"value": 865}, "recovered": {"value": 778}, "dateRecorded": "2020-06-27"}, {"deaths": {"value": 74}, "active": {"value": 13}, "confirmed": {"value": 865}, "recovered": {"value": 778}, "dateRecorded": "2020-06-28"}, {"deaths": {"value": 74}, "active": {"value": 12}, "confirmed": {"value": 866}, "recovered": {"value": 780}, "dateRecorded": "2020-06-29"}, {"deaths": {"value": 74}, "active": {"value": 11}, "confirmed": {"value": 866}, "recovered": {"value": 781}, "dateRecorded": "2020-06-30"}, {"deaths": {"value": 74}, "active": {"value": 11}, "confirmed": {"value": 866}, "recovered": {"value": 781}, "dateRecorded": "2020-07-01"}, {"deaths": {"value": 74}, "active": {"value": 7}, "confirmed": {"value": 866}, "recovered": {"value": 785}, "dateRecorded": "2020-07-02"}, {"deaths": {"value": 74}, "active": {"value": 9}, "confirmed": {"value": 868}, "recovered": {"value": 785}, "dateRecorded": "2020-07-03"}, {"deaths": {"value": 74}, "active": {"value": 11}, "confirmed": {"value": 871}, "recovered": {"value": 786}, "dateRecorded": "2020-07-04"}, {"deaths": {"value": 74}, "active": {"value": 10}, "confirmed": {"value": 871}, "recovered": {"value": 787}, "dateRecorded": "2020-07-05"}, {"deaths": {"value": 74}, "active": {"value": 11}, "confirmed": {"value": 872}, "recovered": {"value": 787}, "dateRecorded": "2020-07-06"}, {"deaths": {"value": 74}, "active": {"value": 11}, "confirmed": {"value": 872}, "recovered": {"value": 787}, "dateRecorded": "2020-07-07"}, {"deaths": {"value": 74}, "active": {"value": 11}, "confirmed": {"value": 873}, "recovered": {"value": 788}, "dateRecorded": "2020-07-08"}, {"deaths": {"value": 74}, "active": {"value": 11}, "confirmed": {"value": 873}, "recovered": {"value": 788}, "dateRecorded": "2020-07-09"}, {"deaths": {"value": 74}, "active": {"value": 11}, "confirmed": {"value": 873}, "recovered": {"value": 788}, "dateRecorded": "2020-07-10"}, {"deaths": {"value": 74}, "active": {"value": 11}, "confirmed": {"value": 874}, "recovered": {"value": 789}, "dateRecorded": "2020-07-11"}, {"deaths": {"value": 74}, "active": {"value": 10}, "confirmed": {"value": 874}, "recovered": {"value": 790}, "dateRecorded": "2020-07-12"}, {"deaths": {"value": 75}, "active": {"value": 15}, "confirmed": {"value": 880}, "recovered": {"value": 790}, "dateRecorded": "2020-07-13"}, {"deaths": {"value": 75}, "active": {"value": 13}, "confirmed": {"value": 880}, "recovered": {"value": 792}, "dateRecorded": "2020-07-14"}, {"deaths": {"value": 75}, "active": {"value": 11}, "confirmed": {"value": 884}, "recovered": {"value": 798}, "dateRecorded": "2020-07-15"}, {"deaths": {"value": 75}, "active": {"value": 11}, "confirmed": {"value": 885}, "recovered": {"value": 799}, "dateRecorded": "2020-07-16"}, {"deaths": {"value": 75}, "active": {"value": 12}, "confirmed": {"value": 886}, "recovered": {"value": 799}, "dateRecorded": "2020-07-17"}, {"deaths": {"value": 75}, "active": {"value": 12}, "confirmed": {"value": 887}, "recovered": {"value": 800}, "dateRecorded": "2020-07-18"}, {"deaths": {"value": 75}, "active": {"value": 14}, "confirmed": {"value": 889}, "recovered": {"value": 800}, "dateRecorded": "2020-07-19"}, {"deaths": {"value": 75}, "active": {"value": 13}, "confirmed": {"value": 889}, "recovered": {"value": 801}, "dateRecorded": "2020-07-20"}, {"deaths": {"value": 75}, "active": {"value": 13}, "confirmed": {"value": 889}, "recovered": {"value": 801}, "dateRecorded": "2020-07-21"}, {"deaths": {"value": 75}, "active": {"value": 11}, "confirmed": {"value": 889}, "recovered": {"value": 803}, "dateRecorded": "2020-07-22"}, {"deaths": {"value": 75}, "active": {"value": 9}, "confirmed": {"value": 889}, "recovered": {"value": 805}, "dateRecorded": "2020-07-23"}, {"deaths": {"value": 75}, "active": {"value": 35}, "confirmed": {"value": 915}, "recovered": {"value": 805}, "dateRecorded": "2020-07-24"}, {"deaths": {"value": 75}, "active": {"value": 35}, "confirmed": {"value": 915}, "recovered": {"value": 805}, "dateRecorded": "2020-07-25"}, {"deaths": {"value": 75}, "active": {"value": 30}, "confirmed": {"value": 915}, "recovered": {"value": 810}, "dateRecorded": "2020-07-26"}, {"deaths": {"value": 75}, "active": {"value": 30}, "confirmed": {"value": 915}, "recovered": {"value": 810}, "dateRecorded": "2020-07-27"}, {"deaths": {"value": 75}, "active": {"value": 37}, "confirmed": {"value": 922}, "recovered": {"value": 810}, "dateRecorded": "2020-07-28"}, {"deaths": {"value": 75}, "active": {"value": 41}, "confirmed": {"value": 926}, "recovered": {"value": 810}, "dateRecorded": "2020-07-29"}, {"deaths": {"value": 75}, "active": {"value": 38}, "confirmed": {"value": 926}, "recovered": {"value": 813}, "dateRecorded": "2020-07-30"}, {"deaths": {"value": 75}, "active": {"value": 47}, "confirmed": {"value": 935}, "recovered": {"value": 813}, "dateRecorded": "2020-07-31"}, {"deaths": {"value": 75}, "active": {"value": 48}, "confirmed": {"value": 936}, "recovered": {"value": 813}, "dateRecorded": "2020-08-01"}, {"deaths": {"value": 75}, "active": {"value": 48}, "confirmed": {"value": 936}, "recovered": {"value": 813}, "dateRecorded": "2020-08-02"}, {"deaths": {"value": 75}, "active": {"value": 48}, "confirmed": {"value": 936}, "recovered": {"value": 813}, "dateRecorded": "2020-08-03"}, {"deaths": {"value": 75}, "active": {"value": 47}, "confirmed": {"value": 936}, "recovered": {"value": 814}, "dateRecorded": "2020-08-04"}, {"deaths": {"value": 75}, "active": {"value": 49}, "confirmed": {"value": 938}, "recovered": {"value": 814}, "dateRecorded": "2020-08-05"}, {"deaths": {"value": 75}, "active": {"value": 29}, "confirmed": {"value": 939}, "recovered": {"value": 835}, "dateRecorded": "2020-08-06"}, {"deaths": {"value": 76}, "active": {"value": 28}, "confirmed": {"value": 942}, "recovered": {"value": 838}, "dateRecorded": "2020-08-07"}, {"deaths": {"value": 76}, "active": {"value": 28}, "confirmed": {"value": 942}, "recovered": {"value": 838}, "dateRecorded": "2020-08-08"}, {"deaths": {"value": 76}, "active": {"value": 27}, "confirmed": {"value": 942}, "recovered": {"value": 839}, "dateRecorded": "2020-08-09"}, {"deaths": {"value": 76}, "active": {"value": 29}, "confirmed": {"value": 944}, "recovered": {"value": 839}, "dateRecorded": "2020-08-10"}, {"deaths": {"value": 76}, "active": {"value": 26}, "confirmed": {"value": 945}, "recovered": {"value": 843}, "dateRecorded": "2020-08-11"}, {"deaths": {"value": 76}, "active": {"value": 11}, "confirmed": {"value": 946}, "recovered": {"value": 859}, "dateRecorded": "2020-08-12"}, {"deaths": {"value": 76}, "active": {"value": 14}, "confirmed": {"value": 949}, "recovered": {"value": 859}, "dateRecorded": "2020-08-13"}, {"deaths": {"value": 76}, "active": {"value": 14}, "confirmed": {"value": 949}, "recovered": {"value": 859}, "dateRecorded": "2020-08-13"}]